sphinxcontrib_apidoc-0.6.0-py3.13-nspkg.pth
sphinxcontrib/apidoc/__init__.py
sphinxcontrib/apidoc/ext.py
sphinxcontrib_apidoc-0.6.0.dist-info/licenses/AUTHORS
sphinxcontrib_apidoc-0.6.0.dist-info/licenses/LICENSE
sphinxcontrib_apidoc-0.6.0.dist-info/METADATA
sphinxcontrib_apidoc-0.6.0.dist-info/WHEEL
sphinxcontrib_apidoc-0.6.0.dist-info/namespace_packages.txt
sphinxcontrib_apidoc-0.6.0.dist-info/pbr.json
sphinxcontrib_apidoc-0.6.0.dist-info/top_level.txt
sphinxcontrib_apidoc-0.6.0.dist-info/RECORD
