Metadata-Version: 2.4
Name: sphinxcontrib-apidoc
Version: 0.6.0
Summary: A Sphinx extension for running 'sphinx-apidoc' on each build
Home-page: https://github.com/sphinx-contrib/apidoc
Author: Stephen Finucane
Author-email: stephen@that.guru
License: BSD License
Project-URL: Bug Tracker, https://github.com/sphinx-contrib/apidoc/issues
Project-URL: Source Code, https://github.com/sphinx-contrib/apidoc
Keywords: sphinx
Classifier: Development Status :: 4 - Beta
Classifier: Environment :: Console
Classifier: Framework :: Sphinx :: Extension
Classifier: Intended Audience :: Developers
Classifier: Intended Audience :: Information Technology
Classifier: License :: OSI Approved :: BSD License
Classifier: Operating System :: OS Independent
Classifier: Programming Language :: Python
Classifier: Programming Language :: Python :: 3
Classifier: Programming Language :: Python :: 3 :: Only
Classifier: Topic :: Documentation
Classifier: Topic :: Documentation :: Sphinx
Classifier: Topic :: Utilities
Requires-Python: >=3.9
License-File: LICENSE
License-File: AUTHORS
Requires-Dist: pbr
Requires-Dist: Sphinx>=5.0.0
Dynamic: author
Dynamic: author-email
Dynamic: description
Dynamic: description-content-type
Dynamic: keywords
Dynamic: license
Dynamic: license-file
Dynamic: project-url
Dynamic: requires-dist
Dynamic: requires-python
Dynamic: summary
